disentangled_rnns/__init__.py
disentangled_rnns/example.py
disentangled_rnns/library/__init__.py
disentangled_rnns/library/checkpoint_utils.py
disentangled_rnns/library/disrnn.py
disentangled_rnns/library/get_datasets.py
disentangled_rnns/library/multisubject_disrnn.py
disentangled_rnns/library/neuro_disrnn.py
disentangled_rnns/library/pclicks.py
disentangled_rnns/library/plotting.py
disentangled_rnns/library/rnn_utils.py
disentangled_rnns/library/two_armed_bandits.py
disentangled_rnns/library/two_armed_bandits_w_dopamine.py
disentangled_rnns/notebooks/train_multisubject_disrnn.ipynb
disentangled_rnns/notebooks/train_neuro_disrnn.ipynb
disentangled_rnns/notebooks/train_single_disrnn.ipynb
disentangled_rnns/notebooks/train_single_gru.ipynb
disentangled_rnns-0.1.2.dist-info/licenses/LICENSE
disentangled_rnns-0.1.2.dist-info/WHEEL
disentangled_rnns-0.1.2.dist-info/METADATA
disentangled_rnns-0.1.2.dist-info/RECORD
