Metadata-Version: 2.4
Name: disentangled_rnns
Version: 0.1.2
Summary: 
Keywords: 
Author-email: GDM NeuroLab <no-reply@google.com>
Requires-Python: >=3.11
Classifier: License :: OSI Approved :: Apache Software License
Classifier: Intended Audience :: Science/Research
License-File: LICENSE
Requires-Dist: dm-haiku>=0.0.13, <0.1
Requires-Dist: jax~=0.5
Requires-Dist: chex~=0.1
Requires-Dist: optax~=0.2
Requires-Dist: flax~=0.10
Requires-Dist: numpy>=2.0, <3.0
Requires-Dist: scipy>=1.15, <2.0
Requires-Dist: matplotlib>=3.9, <4.0
Requires-Dist: absl-py>=2.1, <3.0
Requires-Dist: seaborn~=0.13
Requires-Dist: absl-py ; extra == "dev"
Requires-Dist: pytest ; extra == "dev"
Requires-Dist: pytest-xdist ; extra == "dev"
Requires-Dist: pylint>=2.6.0 ; extra == "dev"
Requires-Dist: pyink ; extra == "dev"
Project-URL: changelog, https://github.com/google-deepmind/disentangled_rnns/blob/main/CHANGELOG.md
Project-URL: homepage, https://github.com/google-deepmind/disentangled_rnns
Project-URL: repository, https://github.com/google-deepmind/disentangled_rnns
Provides-Extra: dev
